templana/__init__.py
templana/py.typed
templana/template.py
templana-0.0.3.dist-info/METADATA
templana-0.0.3.dist-info/WHEEL
templana-0.0.3.dist-info/RECORD
