Metadata-Version: 2.4
Name: templana
Version: 0.0.3
Summary: A simple prompt templating library
Requires-Python: >=3.12
Requires-Dist: jinja2>=3.1.6
Requires-Dist: typing-extensions>=4.13.2
